unitmeasure/__init__.py
unitmeasure/dimension.py
unitmeasure/measurement.py
unitmeasure/unit.py
unitmeasure/converters/__init__.py
unitmeasure/converters/linear.py
unitmeasure/converters/model.py
unitmeasure/converters/reciprocal.py
unitmeasure/serialization/__init__.py
unitmeasure/serialization/json.py
unitmeasure/units/__init__.py
unitmeasure/units/acceleration.py
unitmeasure/units/angle.py
unitmeasure/units/area.py
unitmeasure/units/concentration_mass.py
unitmeasure/units/dispersion.py
unitmeasure/units/duration.py
unitmeasure/units/electric_charge.py
unitmeasure/units/electric_potential_difference.py
unitmeasure/units/electric_resistance.py
unitmeasure/units/energy.py
unitmeasure/units/frequency.py
unitmeasure/units/fuel_efficiency.py
unitmeasure/units/illuminance.py
unitmeasure/units/length.py
unitmeasure/units/mass.py
unitmeasure/units/power.py
unitmeasure/units/pressure.py
unitmeasure/units/speed.py
unitmeasure/units/temperature.py
unitmeasure/units/volume.py
unitmeasure/util/__init__.py
unitmeasure/util/class_property.py
unitmeasure-1.0.0.dist-info/LICENSE
unitmeasure-1.0.0.dist-info/METADATA
unitmeasure-1.0.0.dist-info/WHEEL
unitmeasure-1.0.0.dist-info/top_level.txt
unitmeasure-1.0.0.dist-info/RECORD
