Metadata-Version: 2.1
Name: unitmeasure
Version: 1.0.0
Summary: Python units and measurements
Home-page: https://github.com/gabock/unitmeasure
Author: Greg Bock
License: UNKNOWN
Project-URL: Bug Tracker, https://github.com/gabock/unitmeasure/issues
Platform: UNKNOWN
Classifier: Programming Language :: Python :: 3
Classifier: License :: OSI Approved :: MIT License
Classifier: Operating System :: OS Independent
Requires-Python: >=3.6
License-File: LICENSE
